igs/__init__.py
igs/__main__.py
internetgeminiserver-0.1.2.dist-info/METADATA
internetgeminiserver-0.1.2.dist-info/WHEEL
internetgeminiserver-0.1.2.dist-info/entry_points.txt
internetgeminiserver-0.1.2.dist-info/top_level.txt
internetgeminiserver-0.1.2.dist-info/RECORD
