Metadata-Version: 2.1
Name: internetgeminiserver
Version: 0.1.2
Summary: An multi-domain gemini server
Home-page: https://git.sr.ht/~martijnbraam/igs
Author: Martijn Braam
Author-email: martijn@brixit.nl
License: MIT
Keywords: gemini server tcp asyncio
Platform: UNKNOWN
Classifier: Environment :: Web Environment
Requires-Python: >=3.7
